{"status_code": 200, "text": "{\"links\":{\"next\":\"https://share.osf.io/api/v2/sources/?page%5Bcursor%5D=cD0xMA%3D%3D\",\"prev\":null},\"data\":[{\"type\":\"Source\",\"id\":\"DC0DE-ADB-EEF\",\"attributes\":{\"name\":\"ucsdlibrary\",\"homePage\":\"\",\"longTitle\":\"UC San Diego Library\"},\"relationships\":{\"sourceConfigs\":{\"meta\":{\"count\":1},\"data\":[{\"type\":\"SourceConfig\",\"id\":\"DD0DE-ADB-EEF\"}]}},\"links\":{\"self\":\"https://share.osf.io/api/v2/sources/DC0DE-ADB-EEF/\"}},{\"type\":\"Source\",\"id\":\"DC1BD-5B7-DDE\",\"attributes\":{\"name\":\"edu.ucar\",\"homePage\":\"http://ucar.edu/\",\"longTitle\":\"University Corporation for Atmospheric Research\"},\"relationships\":{\"sourceConfigs\":{\"meta\":{\"count\":1},\"data\":[{\"type\":\"SourceConfig\",\"id\":\"DD1BD-5B7-DDE\"}]}},\"links\":{\"self\":\"https://share.osf.io/api/v2/sources/DC1BD-5B7-DDE/\"}},{\"type\":\"Source\",\"id\":\"DC047-FD5-8CD\",\"attributes\":{\"name\":\"edu.ucsd\",\"homePage\":\"http://ucsd.edu\",\"longTitle\":\"UC San Diego\"},\"relationships\":{\"sourceConfigs\":{\"meta\":{\"count\":1},\"data\":[{\"type\":\"SourceConfig\",\"id\":\"DD047-FD5-8CD\"}]}},\"links\":{\"self\":\"https://share.osf.io/api/v2/sources/DC047-FD5-8CD/\"}},{\"type\":\"Source\",\"id\":\"DC126-AB1-7BC\",\"attributes\":{\"name\":\"edu.scholarsphere\",\"homePage\":\"https://scholarsphere.psu.edu/\",\"longTitle\":\"ScholarSphere @ Penn State University\"},\"relationships\":{\"sourceConfigs\":{\"meta\":{\"count\":1},\"data\":[{\"type\":\"SourceConfig\",\"id\":\"DD126-AB1-7BC\"}]}},\"links\":{\"self\":\"https://share.osf.io/api/v2/sources/DC126-AB1-7BC/\"}},{\"type\":\"Source\",\"id\":\"DC205-58D-6AB\",\"attributes\":{\"name\":\"edu.nd\",\"homePage\":\"https://curate.nd.edu/\",\"longTitle\":\"University of Notre Dame, CurateND\"},\"relationships\":{\"sourceConfigs\":{\"meta\":{\"count\":1},\"data\":[{\"type\":\"SourceConfig\",\"id\":\"DD205-58D-6AB\"}]}},\"links\":{\"self\":\"https://share.osf.io/api/v2/sources/DC205-58D-6AB/\"}},{\"type\":\"Source\",\"id\":\"DC08F-FAB-19A\",\"attributes\":{\"name\":\"org.sldr\",\"homePage\":\"http://sldr.org\",\"longTitle\":\"Speech and Language Data Repository (SLDR/ORTOLANG)\"},\"relationships\":{\"sourceConfigs\":{\"meta\":{\"count\":1},\"data\":[{\"type\":\"SourceConfig\",\"id\":\"DD08F-FAB-19A\"}]}},\"links\":{\"self\":\"https://share.osf.io/api/v2/sources/DC08F-FAB-19A/\"}},{\"type\":\"Source\",\"id\":\"DC16E-A87-089\",\"attributes\":{\"name\":\"pt.rcaap\",\"homePage\":\"http://www.rcaap.pt\",\"longTitle\":\"RCAAP - Reposit\u00f3rio Cient\u00edfico de Acesso Aberto de Portugal\"},\"relationships\":{\"sourceConfigs\":{\"meta\":{\"count\":1},\"data\":[{\"type\":\"SourceConfig\",\"id\":\"DD16E-A87-089\"}]}},\"links\":{\"self\":\"https://share.osf.io/api/v2/sources/DC16E-A87-089/\"}},{\"type\":\"Source\",\"id\":\"DC24D-562-F78\",\"attributes\":{\"name\":\"edu.mason\",\"homePage\":\"http://mars.gmu.edu/\",\"longTitle\":\"Mason Archival Repository Service\"},\"relationships\":{\"sourceConfigs\":{\"meta\":{\"count\":2},\"data\":[{\"type\":\"SourceConfig\",\"id\":\"DD0D7-F80-A67\"},{\"type\":\"SourceConfig\",\"id\":\"DD24D-562-F78\"}]}},\"links\":{\"self\":\"https://share.osf.io/api/v2/sources/DC24D-562-F78/\"}},{\"type\":\"Source\",\"id\":\"DC0D7-F80-A67\",\"attributes\":{\"name\":\"uk.cambridge\",\"homePage\":\"https://www.repository.cam.ac.uk\",\"longTitle\":\"Apollo @ University of Cambridge\"},\"relationships\":{\"sourceConfigs\":{\"meta\":{\"count\":2},\"data\":[{\"type\":\"SourceConfig\",\"id\":\"DD1B6-A5C-956\"},{\"type\":\"SourceConfig\",\"id\":\"DD041-47A-445\"}]}},\"links\":{\"self\":\"https://share.osf.io/api/v2/sources/DC0D7-F80-A67/\"}},{\"type\":\"Source\",\"id\":\"DC1B6-A5C-956\",\"attributes\":{\"name\":\"br.pcurio\",\"homePage\":\"http://www.maxwell.vrac.puc-rio.br\",\"longTitle\":\"Pontifical Catholic University of Rio de Janeiro\"},\"relationships\":{\"sourceConfigs\":{\"meta\":{\"count\":1},\"data\":[{\"type\":\"SourceConfig\",\"id\":\"DD11F-F56-334\"}]}},\"links\":{\"self\":\"https://share.osf.io/api/v2/sources/DC1B6-A5C-956/\"}}]}", "json": {"links": {"next": "https://share.osf.io/api/v2/sources/?page%5Bcursor%5D=cD0xMA%3D%3D", "prev": null}, "data": [{"type": "Source", "id": "DC0DE-ADB-EEF", "attributes": {"name": "ucsdlibrary", "homePage": "", "longTitle": "UC San Diego Library"}, "relationships": {"sourceConfigs": {"meta": {"count": 1}, "data": [{"type": "SourceConfig", "id": "DD0DE-ADB-EEF"}]}}, "links": {"self": "https://share.osf.io/api/v2/sources/DC0DE-ADB-EEF/"}}, {"type": "Source", "id": "DC1BD-5B7-DDE", "attributes": {"name": "edu.ucar", "homePage": "http://ucar.edu/", "longTitle": "University Corporation for Atmospheric Research"}, "relationships": {"sourceConfigs": {"meta": {"count": 1}, "data": [{"type": "SourceConfig", "id": "DD1BD-5B7-DDE"}]}}, "links": {"self": "https://share.osf.io/api/v2/sources/DC1BD-5B7-DDE/"}}, {"type": "Source", "id": "DC047-FD5-8CD", "attributes": {"name": "edu.ucsd", "homePage": "http://ucsd.edu", "longTitle": "UC San Diego"}, "relationships": {"sourceConfigs": {"meta": {"count": 1}, "data": [{"type": "SourceConfig", "id": "DD047-FD5-8CD"}]}}, "links": {"self": "https://share.osf.io/api/v2/sources/DC047-FD5-8CD/"}}, {"type": "Source", "id": "DC126-AB1-7BC", "attributes": {"name": "edu.scholarsphere", "homePage": "https://scholarsphere.psu.edu/", "longTitle": "ScholarSphere @ Penn State University"}, "relationships": {"sourceConfigs": {"meta": {"count": 1}, "data": [{"type": "SourceConfig", "id": "DD126-AB1-7BC"}]}}, "links": {"self": "https://share.osf.io/api/v2/sources/DC126-AB1-7BC/"}}, {"type": "Source", "id": "DC205-58D-6AB", "attributes": {"name": "edu.nd", "homePage": "https://curate.nd.edu/", "longTitle": "University of Notre Dame, CurateND"}, "relationships": {"sourceConfigs": {"meta": {"count": 1}, "data": [{"type": "SourceConfig", "id": "DD205-58D-6AB"}]}}, "links": {"self": "https://share.osf.io/api/v2/sources/DC205-58D-6AB/"}}, {"type": "Source", "id": "DC08F-FAB-19A", "attributes": {"name": "org.sldr", "homePage": "http://sldr.org", "longTitle": "Speech and Language Data Repository (SLDR/ORTOLANG)"}, "relationships": {"sourceConfigs": {"meta": {"count": 1}, "data": [{"type": "SourceConfig", "id": "DD08F-FAB-19A"}]}}, "links": {"self": "https://share.osf.io/api/v2/sources/DC08F-FAB-19A/"}}, {"type": "Source", "id": "DC16E-A87-089", "attributes": {"name": "pt.rcaap", "homePage": "http://www.rcaap.pt", "longTitle": "RCAAP - Reposit\u00f3rio Cient\u00edfico de Acesso Aberto de Portugal"}, "relationships": {"sourceConfigs": {"meta": {"count": 1}, "data": [{"type": "SourceConfig", "id": "DD16E-A87-089"}]}}, "links": {"self": "https://share.osf.io/api/v2/sources/DC16E-A87-089/"}}, {"type": "Source", "id": "DC24D-562-F78", "attributes": {"name": "edu.mason", "homePage": "http://mars.gmu.edu/", "longTitle": "Mason Archival Repository Service"}, "relationships": {"sourceConfigs": {"meta": {"count": 2}, "data": [{"type": "SourceConfig", "id": "DD0D7-F80-A67"}, {"type": "SourceConfig", "id": "DD24D-562-F78"}]}}, "links": {"self": "https://share.osf.io/api/v2/sources/DC24D-562-F78/"}}, {"type": "Source", "id": "DC0D7-F80-A67", "attributes": {"name": "uk.cambridge", "homePage": "https://www.repository.cam.ac.uk", "longTitle": "Apollo @ University of Cambridge"}, "relationships": {"sourceConfigs": {"meta": {"count": 2}, "data": [{"type": "SourceConfig", "id": "DD1B6-A5C-956"}, {"type": "SourceConfig", "id": "DD041-47A-445"}]}}, "links": {"self": "https://share.osf.io/api/v2/sources/DC0D7-F80-A67/"}}, {"type": "Source", "id": "DC1B6-A5C-956", "attributes": {"name": "br.pcurio", "homePage": "http://www.maxwell.vrac.puc-rio.br", "longTitle": "Pontifical Catholic University of Rio de Janeiro"}, "relationships": {"sourceConfigs": {"meta": {"count": 1}, "data": [{"type": "SourceConfig", "id": "DD11F-F56-334"}]}}, "links": {"self": "https://share.osf.io/api/v2/sources/DC1B6-A5C-956/"}}]}, "content": "{\"links\":{\"next\":\"https://share.osf.io/api/v2/sources/?page%5Bcursor%5D=cD0xMA%3D%3D\",\"prev\":null},\"data\":[{\"type\":\"Source\",\"id\":\"DC0DE-ADB-EEF\",\"attributes\":{\"name\":\"ucsdlibrary\",\"homePage\":\"\",\"longTitle\":\"UC San Diego Library\"},\"relationships\":{\"sourceConfigs\":{\"meta\":{\"count\":1},\"data\":[{\"type\":\"SourceConfig\",\"id\":\"DD0DE-ADB-EEF\"}]}},\"links\":{\"self\":\"https://share.osf.io/api/v2/sources/DC0DE-ADB-EEF/\"}},{\"type\":\"Source\",\"id\":\"DC1BD-5B7-DDE\",\"attributes\":{\"name\":\"edu.ucar\",\"homePage\":\"http://ucar.edu/\",\"longTitle\":\"University Corporation for Atmospheric Research\"},\"relationships\":{\"sourceConfigs\":{\"meta\":{\"count\":1},\"data\":[{\"type\":\"SourceConfig\",\"id\":\"DD1BD-5B7-DDE\"}]}},\"links\":{\"self\":\"https://share.osf.io/api/v2/sources/DC1BD-5B7-DDE/\"}},{\"type\":\"Source\",\"id\":\"DC047-FD5-8CD\",\"attributes\":{\"name\":\"edu.ucsd\",\"homePage\":\"http://ucsd.edu\",\"longTitle\":\"UC San Diego\"},\"relationships\":{\"sourceConfigs\":{\"meta\":{\"count\":1},\"data\":[{\"type\":\"SourceConfig\",\"id\":\"DD047-FD5-8CD\"}]}},\"links\":{\"self\":\"https://share.osf.io/api/v2/sources/DC047-FD5-8CD/\"}},{\"type\":\"Source\",\"id\":\"DC126-AB1-7BC\",\"attributes\":{\"name\":\"edu.scholarsphere\",\"homePage\":\"https://scholarsphere.psu.edu/\",\"longTitle\":\"ScholarSphere @ Penn State University\"},\"relationships\":{\"sourceConfigs\":{\"meta\":{\"count\":1},\"data\":[{\"type\":\"SourceConfig\",\"id\":\"DD126-AB1-7BC\"}]}},\"links\":{\"self\":\"https://share.osf.io/api/v2/sources/DC126-AB1-7BC/\"}},{\"type\":\"Source\",\"id\":\"DC205-58D-6AB\",\"attributes\":{\"name\":\"edu.nd\",\"homePage\":\"https://curate.nd.edu/\",\"longTitle\":\"University of Notre Dame, CurateND\"},\"relationships\":{\"sourceConfigs\":{\"meta\":{\"count\":1},\"data\":[{\"type\":\"SourceConfig\",\"id\":\"DD205-58D-6AB\"}]}},\"links\":{\"self\":\"https://share.osf.io/api/v2/sources/DC205-58D-6AB/\"}},{\"type\":\"Source\",\"id\":\"DC08F-FAB-19A\",\"attributes\":{\"name\":\"org.sldr\",\"homePage\":\"http://sldr.org\",\"longTitle\":\"Speech and Language Data Repository (SLDR/ORTOLANG)\"},\"relationships\":{\"sourceConfigs\":{\"meta\":{\"count\":1},\"data\":[{\"type\":\"SourceConfig\",\"id\":\"DD08F-FAB-19A\"}]}},\"links\":{\"self\":\"https://share.osf.io/api/v2/sources/DC08F-FAB-19A/\"}},{\"type\":\"Source\",\"id\":\"DC16E-A87-089\",\"attributes\":{\"name\":\"pt.rcaap\",\"homePage\":\"http://www.rcaap.pt\",\"longTitle\":\"RCAAP - Reposit\u00f3rio Cient\u00edfico de Acesso Aberto de Portugal\"},\"relationships\":{\"sourceConfigs\":{\"meta\":{\"count\":1},\"data\":[{\"type\":\"SourceConfig\",\"id\":\"DD16E-A87-089\"}]}},\"links\":{\"self\":\"https://share.osf.io/api/v2/sources/DC16E-A87-089/\"}},{\"type\":\"Source\",\"id\":\"DC24D-562-F78\",\"attributes\":{\"name\":\"edu.mason\",\"homePage\":\"http://mars.gmu.edu/\",\"longTitle\":\"Mason Archival Repository Service\"},\"relationships\":{\"sourceConfigs\":{\"meta\":{\"count\":2},\"data\":[{\"type\":\"SourceConfig\",\"id\":\"DD0D7-F80-A67\"},{\"type\":\"SourceConfig\",\"id\":\"DD24D-562-F78\"}]}},\"links\":{\"self\":\"https://share.osf.io/api/v2/sources/DC24D-562-F78/\"}},{\"type\":\"Source\",\"id\":\"DC0D7-F80-A67\",\"attributes\":{\"name\":\"uk.cambridge\",\"homePage\":\"https://www.repository.cam.ac.uk\",\"longTitle\":\"Apollo @ University of Cambridge\"},\"relationships\":{\"sourceConfigs\":{\"meta\":{\"count\":2},\"data\":[{\"type\":\"SourceConfig\",\"id\":\"DD1B6-A5C-956\"},{\"type\":\"SourceConfig\",\"id\":\"DD041-47A-445\"}]}},\"links\":{\"self\":\"https://share.osf.io/api/v2/sources/DC0D7-F80-A67/\"}},{\"type\":\"Source\",\"id\":\"DC1B6-A5C-956\",\"attributes\":{\"name\":\"br.pcurio\",\"homePage\":\"http://www.maxwell.vrac.puc-rio.br\",\"longTitle\":\"Pontifical Catholic University of Rio de Janeiro\"},\"relationships\":{\"sourceConfigs\":{\"meta\":{\"count\":1},\"data\":[{\"type\":\"SourceConfig\",\"id\":\"DD11F-F56-334\"}]}},\"links\":{\"self\":\"https://share.osf.io/api/v2/sources/DC1B6-A5C-956/\"}}]}"}